wwwpy/__init__.py
wwwpy/experimental/__init__.py
wwwpy_experimental-0.0.2.dist-info/METADATA
wwwpy_experimental-0.0.2.dist-info/WHEEL
wwwpy_experimental-0.0.2.dist-info/top_level.txt
wwwpy_experimental-0.0.2.dist-info/RECORD
